PicSeek/__init__.py
PicSeek/searcher.py
PicSeek/utils.py
PicSeek-1.0.0.dist-info/LICENSE
PicSeek-1.0.0.dist-info/METADATA
PicSeek-1.0.0.dist-info/WHEEL
PicSeek-1.0.0.dist-info/top_level.txt
PicSeek-1.0.0.dist-info/RECORD
