Metadata-Version: 2.1
Name: PicSeek
Version: 1.0.0
Summary: A simple Python image search library
Home-page: https://github.com/Mr-Abood/PicSeek
Author: PicSeek
Author-email: abodawad1111@gmail.com
Classifier: Programming Language :: Python :: 3
Classifier: License :: OSI Approved :: MIT License
Classifier: Operating System :: OS Independent
Requires-Python: >=3.6
License-File: LICENSE
Requires-Dist: requests
